Metadata-Version: 2.1
Name: discord-webhook-logging
Version: 0.0.3
Summary: Simple Discord webhook logger
Home-page: https://github.com/matobodo/DiscordWebhookLogging
Author: Martin Bodický
Author-email: 
License: UNKNOWN
Platform: UNKNOWN
Classifier: Development Status :: 3 - Alpha
Classifier: License :: OSI Approved :: MIT License
Classifier: Operating System :: OS Independent
Classifier: Programming Language :: Python :: 3
Classifier: Programming Language :: Python :: 3.8
